fix_db_wifi/__init__.py
fix_db_wifi/main.py
fix_db_wifi-0.1.2.dist-info/METADATA
fix_db_wifi-0.1.2.dist-info/WHEEL
fix_db_wifi-0.1.2.dist-info/entry_points.txt
fix_db_wifi-0.1.2.dist-info/top_level.txt
fix_db_wifi-0.1.2.dist-info/RECORD
